[
    {
        "name": "Emojis",
        "introScreenText": 
        {
            "EN": "Memorize these emojis in order"
        },
        "introScreenSubText": 
        {
            "EN": "Get ready!"
        },
        "maxItemsAnswerScreen": 30,
        "totalNumItems": 159,
        "intervalSecondsEasyLevels": 1300,
        "intervalSecondsDifficultLevels": 1600,
        "firstDifficultLevel": 10,
        "gameCompletedScore": 7340
    },
    {
        "name": "Flags",
        "introScreenText": 
        {
            "EN": "Memorize these flags in order"
        },
        "introScreenSubText": 
        {
            "EN": "Get ready!"
        },
        "maxItemsAnswerScreen": 30,
        "totalNumItems": 132,
        "intervalSecondsEasyLevels": 1700,
        "intervalSecondsDifficultLevels": 2000,
        "firstDifficultLevel": 10,
        "gameCompletedScore": 7340
    },
    {
        "name": "Numbers",
        "introScreenText": 
        {
            "EN": "Memorize these numbers in order"
        },
        "introScreenSubText": 
        {
            "EN": "Get ready!"
        },
        "maxItemsAnswerScreen": 30,
        "totalNumItems": 100,
        "intervalSecondsEasyLevels": 1300,
        "intervalSecondsDifficultLevels": 1600,
        "firstDifficultLevel": 10,
        "gameCompletedScore": 7340
    },
    {
        "name": "Arithmetic",
        "introScreenText": 
        {
            "EN": "Add up all these numbers"
        },
        "introScreenSubText": 
        {
            "EN": "Get ready!"
        },
        "maxItemsAnswerScreen": 30,
        "totalNumItems": 100,
        "intervalSecondsEasyLevels": 2500,
        "intervalSecondsDifficultLevels": 3000,
        "firstDifficultLevel": 10,
        "rangeSeedItems": 199,
        "rangeDisplayedItems": 50,
        "minNumberRange": -99,
        "gameCompletedScore": 3820
    },
    {
        "name": "Shapes",
        "introScreenText": 
        {
            "EN": "Memorize these geometric shapes in order"
        },
        "introScreenSubText": 
        {
            "EN": "Get ready!"
        },
        "maxItemsAnswerScreen": 30,
        "totalNumItems": 100,
        "intervalSecondsEasyLevels": 2000,
        "intervalSecondsDifficultLevels": 2300,
        "firstDifficultLevel": 10,
        "gameCompletedScore": 7340
    },
    {
        "name": "Cards",
        "introScreenText": 
        {
            "EN": "Memorize these playing cards in order"
        },
        "introScreenSubText": 
        {
            "EN": "Get ready!"
        },
        "maxItemsAnswerScreen": 30,
        "totalNumItems": 52,
        "intervalSecondsEasyLevels": 2000,
        "intervalSecondsDifficultLevels": 2300,
        "firstDifficultLevel": 10,
        "gameCompletedScore": 7340
    },
    {
        "name": "Kids",
        "introScreenText": 
        {
            "EN": "Play and learn new words",
            "ES": "Juega y aprende nuevas palabras",
            "NO": "Spill og lær nye ord"
        },
        "introScreenSubText": 
        {
            "EN": "Get ready!",
            "ES": "¡Prepárate!",
            "NO": "Gjør deg klar!"
        },
        "maxItemsAnswerScreen": 12,
        "totalNumItems": 126,
        "intervalSecondsEasyLevels": 2500,
        "intervalSecondsDifficultLevels": 2500,
        "firstDifficultLevel": 32,
        "gameCompletedScore": 7340
    }
]